{"cameraMode":{"drawMode":0,"name":"Shaded","section":"Shading Mode"},"sceneLighting":true,"audioPlay":false,"sceneViewState":{"m_AlwaysRefresh":false,"showFog":true,"showSkybox":true,"showFlares":true,"showImageEffects":true,"showParticleSystems":true,"showVisualEffectGraphs":true,"m_FxEnabled":true},"in2DMode":false,"pivot":{"x":-0.9071035981178284,"y":1.046276330947876,"z":0.41442251205444338},"rotation":{"x":-0.10535715520381928,"y":0.6981241106987,"z":-0.10501859337091446,"w":-0.7003812193870544},"size":1.1472147703170777,"orthographic":false}