{"cameraMode":{"drawMode":0,"name":"Shaded","section":"Shading Mode"},"sceneLighting":false,"audioPlay":false,"sceneViewState":{"m_AlwaysRefresh":false,"showFog":true,"showSkybox":false,"showFlares":true,"showImageEffects":true,"showParticleSystems":true,"showVisualEffectGraphs":true,"m_FxEnabled":true},"in2DMode":false,"pivot":{"x":-8.976737022399903,"y":10.391073226928711,"z":3.662928819656372},"rotation":{"x":0.35755613446235659,"y":0.3431578278541565,"z":-0.14322862029075623,"w":0.856672465801239},"size":1.9352566003799439,"orthographic":false}